{
  "info": {
    "day": "ソフト",
    "title": "時を越えた星明かり",
    "name": "ソフト"
  },
  "scenario":[
    {
      "timing": "",
      "word": "",
      "projector": {
          "Gxy": 1
        }
    }, {
      "timing": "post",
      "word": "さとる４「いや、ぼくも気になるから、過去の世界。例えば、ここから見える景色とかな」",
      "projector": {
          "Fst": 1
        }
    }, {
      "timing": "（ガチャ）と同時",
      "word": "（ガチャ）",
      "projector": {
          "St1": 1,
          "St2": 1
        }
    }, {
      "timing": "post",
      "word": "ゆき５「オリオンって？」",
      "projector": {
          "Ori": 1
        }
    }, {
      "timing": "post",
      "word": "ゆき６「へええ。すごい人だったのね」",
      "projector": {
          "Ori": 0
        }
    }, {
      "timing": "「おおいぬ座」と同時",
      "word": "さとる２５「この星は、おおいぬ座のシリウス。」",
      "projector": {
          "CMa": 1
        }
    }, {
      "timing": "「こいぬ座」と同時",
      "word": "さとる２６「シリウスの左上にも、明るい星があるのが見える？あれはこいぬ座のプロキオンっていう星なんだ。<続く>」",
      "projector": {
          "CMi": 1
        }
    }, {
      "timing": "「オリオン座」と同時",
      "word": "おおいぬ座のシリウス、こいぬ座のプロキオン、それからオリオン座の赤い星、ベテルギウスを結ぶと…」からさとる２７まで",
      "projector": {
          "Ori": 1
        }
    }, {
      "timing": "post",
      "word": "ゆき１１「そうなんだ！とっても面白い！」",
      "projector": {
          "Ori": 0,
          "CMa": 0,
          "CMi": 0
        }
    }, {
      "timing": "「おうし座」と同時",
      "word": "さとる２９「さっきの三ツ星を、今度は右上にたどっていくと…赤っぽい星があるんだけど、見つけられる？これがおうし座のアルデバランっていう星なんだ。これをさらに伸ばしていくと…」",
      "projector": {
          "Tau": 1
        }
    }, {
      "timing": "「ぎょしゃ座」と同時",
      "word": "さとる３４「これがぎょしゃ座。この中で一番明るい星をカペラっていうんだ」",
      "projector": {
          "Tau": 0,
          "Aur": 1
        }
    }, {
      "timing": "post",
      "word": "けんた３７「カペラの西側だから…これか！」",
      "projector": {
          "Aur": 0
        }
    }, {
      "timing": "post",
      "word": "さとる３６「これは、ふたご座の中の星で、明るい方がポルックス、もう一方がカストルっていう星だ。ふたご座は、仲良く並んだ双子の姿が描かれた星座なんだよ」",
      "projector": {
          "Gem": 1
        }
    }, {
      "timing": "post",
      "word": "ゆき２０「よかった！二人は今でも星空の中で一緒にいられるのね」",
      "projector": {
          "Gem": 0
        }
    }, {
      "timing": "「ポルックス」",
      "word": "けんた４２「ん？えーと？ふたご座のポルックス、ぎょしゃ座のカペラ、うーん…後は…」さとる４２「おうし座のアルデバラン、オリオン座のリゲル、あとは冬の大三角にも入ってた、おおいぬ座のシリウス、こいぬ座のプロキオン、ですよね」",
      "projector": {
          "Gem": 1
        }
    }, {
      "timing": "「カペラ」",
      "word": "けんた４２「ん？えーと？ふたご座のポルックス、ぎょしゃ座のカペラ、うーん…後は…」さとる４２「おうし座のアルデバラン、オリオン座のリゲル、あとは冬の大三角にも入ってた、おおいぬ座のシリウス、こいぬ座のプロキオン、ですよね」",
      "projector": {
          "Aur": 1
        }
    }, {
      "timing": "「アルデバラン」",
      "word": "けんた４２「ん？えーと？ふたご座のポルックス、ぎょしゃ座のカペラ、うーん…後は…」さとる４２「おうし座のアルデバラン、オリオン座のリゲル、あとは冬の大三角にも入ってた、おおいぬ座のシリウス、こいぬ座のプロキオン、ですよね」",
      "projector": {
          "Tau": 1
        }
    }, {
      "timing": "「リゲル」",
      "word": "けんた４２「ん？えーと？ふたご座のポルックス、ぎょしゃ座のカペラ、うーん…後は…」さとる４２「おうし座のアルデバラン、オリオン座のリゲル、あとは冬の大三角にも入ってた、おおいぬ座のシリウス、こいぬ座のプロキオン、ですよね」",
      "projector": {
          "Ori": 1
        }
    }, {
      "timing": "「シリウス」",
      "word": "けんた４２「ん？えーと？ふたご座のポルックス、ぎょしゃ座のカペラ、うーん…後は…」さとる４２「おうし座のアルデバラン、オリオン座のリゲル、あとは冬の大三角にも入ってた、おおいぬ座のシリウス、こいぬ座のプロキオン、ですよね」",
      "projector": {
          "CMa": 1
        }
    }, {
      "timing": "「プロキオン」",
      "word": "けんた４２「ん？えーと？ふたご座のポルックス、ぎょしゃ座のカペラ、うーん…後は…」さとる４２「おうし座のアルデバラン、オリオン座のリゲル、あとは冬の大三角にも入ってた、おおいぬ座のシリウス、こいぬ座のプロキオン、ですよね」",
      "projector": {
          "CMi": 1
        }
    }, {
      "timing": "post",
      "word": "ゆき２２「しかもきらきら光る星でできているなんて、素敵ね！」、じろう１「ゆき！」",
      "projector": {
          "Gem": 0,
          "Aur": 0,
          "Tau": 0,
          "Ori": 0,
          "CMa": 0,
          "CMi": 0
        }
    }, {
      "timing": "post",
      "word": "あかね３１「あらそう？」",
      "projector": {
          "Lyr": 1
        }
    }, {
      "timing": "「わし座」のタイミング",
      "word": "あかね３６「そうよ（笑）彦星は、」（星座絵）",
      "projector": {
          "Aql": 1
        }
    }, {
      "timing": "post",
      "word": "「表されているわ」",
      "projector": {
          "Lyr": 0,
          "Aql": 0
        }
    }, {
      "timing": "「はくちょう座」",
      "word": "あかね３８「私たちは、白鳥が翼を広げた姿を想像して、」（星座絵）。「はくちょう座って呼んでいるの。」「ベガとアルタイルの間にある、白鳥の頭にあたるのがアルビレオっていう星、そして、尾にあたる明るい星が“尻尾”っていう意味の名前の星、デネブよ」（レーザー）",
      "projector": {
          "Cyg": 1
        }
    }, {
      "timing": "「こと座」と同時",
      "word": "あかね３９「はくちょう座のデネブと、さっきの織姫と彦星、つまり、」「こと座のベガ」・「わし座のアルタイル」",
      "projector": {
          "Lyr": 1
        }
    }, {
      "timing": "「わし座」と同時",
      "word": "あかね３９「はくちょう座のデネブと、さっきの織姫と彦星、つまり、」「こと座のベガ」・「わし座のアルタイル」",
      "projector": {
          "Aql": 1
        }
    }, {
      "timing": "post",
      "word": "さとる５０「たとえば…さそり座ですか」",
      "projector": {
          "Lyr": 0,
          "Aql": 0,
          "Cyg": 0
        }
    }, {
      "timing": "「体がくねくね曲がった〜」のタイミング",
      "word": "あかね４４「この星はさそりの心臓の部分よ。さそり座は、そのちょっと上から星をつなげるの。」「体がくねくね曲がったさそり、想像できるかしら？」",
      "projector": {
          "Sco": 1
        }
    }, {
      "timing": "post",
      "word": "けんた５７「わかった、これがさそり座か！」",
      "projector": {
          "Sco": 0
        }
    }
  ]
}
